newpythonlibrary/__init__.py
newpythonlibrary/function.py
prabhath-0.0.1.dist-info/METADATA
prabhath-0.0.1.dist-info/WHEEL
prabhath-0.0.1.dist-info/top_level.txt
prabhath-0.0.1.dist-info/RECORD
